hmacchanger-1.4.data/scripts/hmacchanger
pytransform/__init__.py
pytransform/_pytransform.so
hmacchanger-1.4.dist-info/LICENSE.txt
hmacchanger-1.4.dist-info/METADATA
hmacchanger-1.4.dist-info/WHEEL
hmacchanger-1.4.dist-info/top_level.txt
hmacchanger-1.4.dist-info/RECORD
