Metadata-Version: 2.1
Name: hmacchanger
Version: 1.4
Summary: Changing MAC Address
Home-page: https://github.com/hairprasath6112001/hmacchanger
Author: HariPrasath.S.S
Author-email: hariprasath6112001@gmail.com
License: UNKNOWN
Platform: UNKNOWN
Classifier: Programming Language :: Python :: 3
Classifier: Programming Language :: Python :: 3.6
Classifier: Programming Language :: Python :: 3.8
Classifier: License :: OSI Approved :: MIT License
Classifier: Operating System :: OS Independent
